{
    "prefix" : "!",
    "sahip" : "909306784869662750",
    "token" : "OTI0NjUxOTg5MjA2NDQxOTk0.YchrRQ.5_22HYMe-J_dnKESGTEYFrKuEgs",

    "botStatus": "YolHost Bilişim Hizmetleri",
    "botStatus2": "Sizin Hizmetinizde!",
    "botVoiceChannelID": "924585295410769960",
  
    "gelengiden": "924585296161562664",
  
    "destekKanal":"924585295691784201",
    "destekRol":"858366007982293004",
    "destekKategori":"924585295691784200",

    "bot":"924651989206441994",

    "genelsorumlu":"924585295410769957",
    "uye":"924585295377236001",
    "minecraft":"924585295360430170",
    "unturned":"924585295360430171",
    "mta":"924585295377235998",
    "fivem":"924585295360430174",
    "discordsor":"858366007982293004"
  }